dcttools/__init__.py
dcttools/core.py
dcttools-0.1.4.dist-info/LICENSE
dcttools-0.1.4.dist-info/WHEEL
dcttools-0.1.4.dist-info/METADATA
dcttools-0.1.4.dist-info/RECORD
