Metadata-Version: 2.1
Name: dcttools
Version: 0.1.4
Summary: Python Dictionairy Tools
Home-page: https://github.com/tZ3ma/dcttools
License: MIT
Keywords: python-3,dictionairy-application
Author: Mathias Ammon
Author-email: mathias.ammon@tuhh.de
Requires-Python: >=3.8,<4.0
Classifier: License :: OSI Approved :: MIT License
Classifier: Programming Language :: Python :: 3
Classifier: Programming Language :: Python :: 3.8
Classifier: Programming Language :: Python :: 3.9
Classifier: Programming Language :: Python :: 3.10
Classifier: Programming Language :: Python :: 3.11
Requires-Dist: pandas
Project-URL: Repository, https://github.com/tZ3ma/dcttools
